inspire_classifier/__init__.py
inspire_classifier/cli.py
inspire_classifier/core/__init__.py
inspire_classifier/core/api.py
inspire_classifier/core/model.py
inspire_classifier/core/preprocessor.py
inspire_classifier/core/utils.py
inspire_classifier-2.0.4.dist-info/METADATA
inspire_classifier-2.0.4.dist-info/WHEEL
inspire_classifier-2.0.4.dist-info/entry_points.txt
inspire_classifier-2.0.4.dist-info/RECORD
